{
	"name": "pl_load_customers",
	"properties": {
		"activities": [
			{
				"name": "pl_load_customers",
				"type": "Copy",
				"dependsOn": [],
				"policy": {
					"timeout": "0.12:00:00",
					"retry": 0,
					"retryIntervalInSeconds": 30,
					"secureOutput": false,
					"secureInput": false
				},
				"userProperties": [],
				"typeProperties": {
					"source": {
						"type": "JsonSource",
						"storeSettings": {
							"type": "AzureBlobStorageReadSettings",
							"recursive": true,
							"enablePartitionDiscovery": false
						},
						"formatSettings": {
							"type": "JsonReadSettings"
						}
					},
					"sink": {
						"type": "AzureSqlSink",
						"writeBehavior": "insert",
						"sqlWriterUseTableLock": false
					},
					"enableStaging": false,
					"translator": {
						"type": "TabularTranslator",
						"mappings": [
							{
								"source": {
									"path": "$['CustomerID']"
								},
								"sink": {
									"name": "CustomerID",
									"type": "Int32"
								}
							},
							{
								"source": {
									"path": "$['FirstName']"
								},
								"sink": {
									"name": "FirstName",
									"type": "String"
								}
							},
							{
								"source": {
									"path": "$['Status']"
								},
								"sink": {
									"name": "Status",
									"type": "String"
								}
							}
						]
					}
				},
				"inputs": [
					{
						"referenceName": "pl_load_customers",
						"type": "DatasetReference"
					}
				],
				"outputs": [
					{
						"referenceName": "ds_sql_customers",
						"type": "DatasetReference"
					}
				]
			}
		],
		"annotations": [],
		"lastPublishTime": "2026-01-05T23:10:44Z"
	},
	"type": "Microsoft.DataFactory/factories/pipelines"
}